{
  "story_id": "ROI-cand-dyn-slice-f7e09f20fb21",
  "title": "[Entreg\u00e1vel B \u2014 mapeamento de 15 concorrentes obser] O sistema consegue selecionar e justificar pelo menos 15 for \u00b7 A sele\u00e7\u00e3o dos 15 possui regra reproduz\u00edvel e configur\u00e1vel. \u00b7 Cada fornecedor possui ",
  "epic_id": "EPIC-EXTRA-DOD-ROI",
  "risk_level": "HIGH-RISK",
  "status": "Done",
  "story_file": "docs/stories/ROI-cand-dyn-slice-f7e09f20fb21.md",
  "created_at": "2026-07-18T18:21:21Z",
  "updated_at": "2026-07-18T18:27:04Z",
  "created_by": "extra-dod-roi-force-next",
  "po_validated": true,
  "qa_verdict": "PASS",
  "po_closed": true,
  "publication_authorized": true,
  "scope_files": [
    "DOD.md",
    "docs/ops/session-*/",
    "tests/*",
    "scripts/*"
  ],
  "reviewed_commit": "bd23854811b05cf58d889a1cd67f3aba7dafde88",
  "gates": {
    "lint": "PASS",
    "typecheck": "NA",
    "tests": "PASS",
    "build": "NA"
  },
  "rollback_plan": "Revert feature branch commits; never update DoD on failure; no merge.",
  "snapshot_evidence": null,
  "maintenance_mode": false,
  "extra_dod_roi": {
    "cycle_id": "cyc-2026-07-18T182121Z",
    "candidate_id": "cand-dyn-slice:f7e09f20fb21",
    "roi": 1.2261,
    "foolproof": true,
    "selection_rule": "ranking[0] only",
    "aiox_sequence_required": [
      "STORY_DRAFT",
      "STORY_READY",
      "IMPLEMENTING",
      "IN_REVIEW",
      "QA",
      "PO_CLOSE",
      "PUBLISH",
      "RERANK"
    ]
  }
}
