{
  "results": [
    {
      "source": "sc_compras",
      "status": "success",
      "fetched": 0,
      "transformed": 0,
      "inserted": 0,
      "updated": 0,
      "duplicates": 0,
      "matched": 0,
      "unmatched": 0,
      "ambiguous": 0,
      "new_entities_covered": 0,
      "classified_engineering": 0,
      "engineering_confirmed": 0,
      "engineering_probable": 0,
      "engineering_review_required": 0,
      "false_positive_discarded": 0,
      "within_200km": 0,
      "remaining_sc": 0,
      "location_unconfirmed": 0,
      "opportunities_persisted": 0,
      "external_failures": 0,
      "started_at": "2026-07-19T02:10:59.363975+00:00",
      "completed_at": "2026-07-19T02:10:59.504416+00:00",
      "duration_seconds": 0.0,
      "error_code": null,
      "error_message": null,
      "dependencies_missing": [],
      "warnings": [],
      "metadata": {
        "pipeline": "OperationalPipeline",
        "db_committed": null,
        "operational_satisfactory": true,
        "evidence": null,
        "watermark": {
          "checkpoint": {
            "attempt_count": 1,
            "content_hash": "d9dd5454231b0ed4fe47042ff9ae51834251fbad089f066eacbe330460c9da8a",
            "cursor": null,
            "date_from": "2026-07-11",
            "date_to": "2026-07-18",
            "environment": "development",
            "execution_mode": "live",
            "last_error": null,
            "last_http_status": 200,
            "page": null,
            "pages_expected": 53,
            "pages_fetched": 53,
            "raw_reference": null,
            "request_scope": "mode=incremental|date=2026-07-11..2026-07-18",
            "run_id": "monitor-sc_compras-20260718T211306Z-0c15774f10",
            "scope_level": "run",
            "snapshot_hash": null,
            "source": "sc_compras",
            "stage": "success",
            "status": "success",
            "target": null,
            "updated_at": "2026-07-18T21:13:22.221596+00:00",
            "window": "2026-07-11"
          },
          "committed_at": "2026-07-18T21:13:23.419352+00:00",
          "db_committed": true,
          "environment": "development",
          "evidence_hash": "cc482e042e15c144f97bd7ff4dfa58e50fa66c7bd1d7eea9f69e48982114af7f",
          "evidence_path": "output/resilience/development/evidence/sc_compras/monitor-sc_compras-20260718T211306Z-0c15774f10/mode_incremental_date_2026-07-11..2026-07-18.json",
          "execution_mode": "live",
          "request_scope": "mode=incremental|date=2026-07-11..2026-07-18",
          "run_id": "monitor-sc_compras-20260718T211306Z-0c15774f10",
          "source": "sc_compras",
          "status": "committed"
        },
        "environment": null,
        "execution_mode": null
      }
    }
  ],
  "summary": {
    "total_fetched": 0,
    "total_transformed": 0,
    "total_inserted": 0,
    "total_updated": 0,
    "total_matched": 0,
    "total_classified_engineering": 0,
    "total_engineering_confirmed": 0,
    "total_engineering_probable": 0,
    "total_within_200km": 0,
    "total_remaining_sc": 0,
    "total_location_unconfirmed": 0,
    "total_false_positive": 0,
    "total_persisted_opportunities": 0,
    "total_external_failures": 0,
    "sources_success": 1,
    "sources_degraded": 0,
    "sources_empty": 0,
    "sources_skipped": 0,
    "sources_failed": 0,
    "generated_at": "2026-07-18T23:10:59.535864"
  }
}