{
  "at": "2026-07-18T15:17:55.963866+00:00",
  "campaign_id": "ADVANCE-30D-LOCAL-READY-20260718",
  "status": "IN_PROGRESS",
  "epic": "epic/advance-30d-local-ready-20260718",
  "initial_sha": "fbc586856332db11ecb21ae4524dfdf29dd90857",
  "current_sha": "ec5226e5c14ec2038d5658d536e7b82b5cb2f4dd",
  "slices_completed": 29,
  "dod": {
    "checked": 237,
    "open": 1117,
    "baseline_checked": 92
  },
  "metrics": {
    "universe_within_radius": 1093,
    "universe_resolution_pct": 100.0,
    "operational_coverage_pct": 0.0,
    "local_ready": false,
    "golden_path_live_pncp": true,
    "pncp_live_inserted": 6
  },
  "resume": "python3 squads/extra-dod-roi/scripts/cli.py force-next",
  "forbidden_claims": [
    "LOCAL_READY",
    "95% operational",
    "PRE_VPS_FINAL_READY",
    "PROJECT_DONE"
  ]
}
