{
  "ok": true,
  "at": "2026-07-21T23:31:18Z",
  "title": "A vers\u00e3o do schema \u00e9 registrada.",
  "main_sha": "c640e63b2d0bcfcd2b11e54d38c47fff5304c979",
  "impl_pr": 97,
  "ledger_meta_key": "schema_version",
  "ledger_meta_value": "migrations_count=62",
  "full_meta": {
    "canonical_command": "python3 -m scripts.golden_path",
    "as_of": "2026-07-21T23:30:45.357513Z",
    "reference_period": {
      "as_of": "2026-07-21T23:30:45.357513Z",
      "window": "run-scoped"
    },
    "git_sha": "c640e63b2d0bcfcd2b11e54d38c47fff5304c979",
    "dsn_present": false,
    "migration_files_count": 62,
    "schema_version": "migrations_count=62",
    "limitations": [
      "Metadata is local/run-scoped; does not prove VPS or LOCAL_READY.",
      "Coverage and freshness require a reachable DSN and applied migrations."
    ],
    "spreadsheet_sha256": "d65f272812cf8dc95f3ca78c5db9a2fb2a39a759e5633eb3fb91891ad10a5486",
    "canonical_ids_sha256": "0b3f894d87ba71f2e0fa96887cb3075033488de1af1e6e55f97ccda0701fb396"
  },
  "wall_clock_ms": 448.04889999977604
}
