{
  "task": "N02",
  "verdict": "PASS",
  "reviewer": "adversarial-qa-auditor",
  "independent_of": "delivery-engineer-r2",
  "ts": "2026-07-18T20:44:49Z",
  "checks": [
    "snapshot generate created run_id=1",
    "check-seed OK vs seed sha256",
    "in_seed_only=0",
    "test_universe 13 passed",
    "zero_dup cnpj_8=True"
  ],
  "concerns": [
    "995 entities in DB only beyond seed included set \u2014 expected expansion residue; not seed loss",
    "check-seed warned no snapshots before generate \u2014 fixed this cycle"
  ]
}
