{
  "subtaskId": "TD-0.2",
  "critiquedAt": "2026-07-11T00:00:00Z",
  "step5_5": {
    "predictedBugs": [
      "N/A: only docstring and markdown changes, no logic code"
    ],
    "edgeCases": [
      "N/A: diagnostic-only story, no edge-case logic"
    ],
    "errorHandling": true,
    "securityCheck": true,
    "passed": true
  },
  "step6_5": {
    "followsPatterns": true,
    "noHardcoded": true,
    "testsAdded": false,
    "docsUpdated": true,
    "noConsoleLogs": true,
    "passed": true
  },
  "overallVerdict": "PASSED",
  "skipped": false,
  "skipWarning": null
}
